bzoinq/__init__.py
bzoinq/bzoinq.py
bzoinq/playit.py
bzoinq/sound/alarm-clock-elapsed.wav
bzoinq-0.1.5.dist-info/AUTHORS.rst
bzoinq-0.1.5.dist-info/LICENSE
bzoinq-0.1.5.dist-info/METADATA
bzoinq-0.1.5.dist-info/WHEEL
bzoinq-0.1.5.dist-info/top_level.txt
bzoinq-0.1.5.dist-info/RECORD
