Metadata-Version: 2.1
Name: bzoinq
Version: 0.1.5
Summary: Play a sound or run a function at some datetime
Home-page: https://github.com/lapisdecor/bzoinq
Author: Luis Louro
Author-email: lapisdecor@gmail.com
License: MIT license
Keywords: bzoinq
Platform: UNKNOWN
Classifier: Development Status :: 2 - Pre-Alpha
Classifier: Intended Audience :: Developers
Classifier: License :: OSI Approved :: MIT License
Classifier: Natural Language :: English
Classifier: Programming Language :: Python :: 3
Classifier: Programming Language :: Python :: 3.5
Classifier: Programming Language :: Python :: 3.6
Classifier: Programming Language :: Python :: 3.7
